Metadata-Version: 1.1
Name: django-sphinxql
Version: 1.1.0
Summary: Sphinx search on Django
Home-page: https://github.com/jorgecarleitao/django-sphinxql
Author: Jorge C. Leitão
Author-email: jorgecarleitao@gmail.com
License: GPLv2
Platform: UNKNOWN
Classifier: Development Status :: 5 - Production/Stable
Classifier: Environment :: Web Environment
Classifier: Framework :: Django
Classifier: Intended Audience :: Developers
Classifier: License :: OSI Approved :: GNU General Public License v2 (GPLv2)
Classifier: Operating System :: Unix
Classifier: Programming Language :: Python
Classifier: Programming Language :: Python :: 3
Classifier: Topic :: Utilities
